<?xml version="1.0" encoding="utf-8" ?><dwsync><file name="222222_11x11_icon_arrows_leftright.gif" server="www.sypdevelopment.com/dpm/" local="3322782828" remote="166626717428" /><file name="222222_11x11_icon_arrows_updown.gif" server="www.sypdevelopment.com/dpm/" local="3322782828" remote="153741815540" /><file name="222222_11x11_icon_close.gif" server="www.sypdevelopment.com/dpm/" local="3322782828" remote="119382077172" /><file name="222222_11x11_icon_doc.gif" server="www.sypdevelopment.com/dpm/" local="3322782828" remote="110792142580" /><file name="222222_11x11_icon_folder_closed.gif" server="www.sypdevelopment.com/dpm/" local="3322782828" remote="153741815540" /><file name="222222_11x11_icon_folder_open.gif" server="www.sypdevelopment.com/dpm/" local="3322782828" remote="145151880948" /><file name="222222_11x11_icon_minus.gif" server="www.sypdevelopment.com/dpm/" local="3322782828" remote="119382077172" /><file name="222222_11x11_icon_plus.gif" server="www.sypdevelopment.com/dpm/" local="3322782828" remote="115087109876" /><file name="222222_11x11_icon_resize_se.gif" server="www.sypdevelopment.com/dpm/" local="3322782828" remote="136561946356" /><file name="222222_7x7_arrow_down.gif" server="www.sypdevelopment.com/dpm/" local="3322782828" remote="110792142580" /><file name="222222_7x7_arrow_left.gif" server="www.sypdevelopment.com/dpm/" local="3322782828" remote="110792142580" /><file name="222222_7x7_arrow_right.gif" server="www.sypdevelopment.com/dpm/" local="3322782828" remote="115087109876" /><file name="222222_7x7_arrow_up.gif" server="www.sypdevelopment.com/dpm/" local="3322782828" remote="102202207988" /><file name="454545_11x11_icon_arrows_leftright.gif" server="www.sypdevelopment.com/dpm/" local="3322782828" remote="166626717428" /><file name="454545_11x11_icon_arrows_updown.gif" server="www.sypdevelopment.com/dpm/" local="3322782828" remote="153741815540" /><file name="454545_11x11_icon_close.gif" server="www.sypdevelopment.com/dpm/" local="3322782828" remote="119382077172" /><file name="454545_11x11_icon_doc.gif" server="www.sypdevelopment.com/dpm/" local="3322782828" remote="110792142580" /><file name="454545_11x11_icon_folder_closed.gif" server="www.sypdevelopment.com/dpm/" local="3322782828" remote="153741815540" /><file name="454545_11x11_icon_folder_open.gif" server="www.sypdevelopment.com/dpm/" local="3322782828" remote="145151880948" /><file name="454545_11x11_icon_minus.gif" server="www.sypdevelopment.com/dpm/" local="3322782828" remote="119382077172" /><file name="454545_11x11_icon_plus.gif" server="www.sypdevelopment.com/dpm/" local="3322782828" remote="115087109876" /><file name="454545_7x7_arrow_down.gif" server="www.sypdevelopment.com/dpm/" local="3322782828" remote="110792142580" /><file name="454545_7x7_arrow_left.gif" server="www.sypdevelopment.com/dpm/" local="3322782828" remote="110792142580" /><file name="454545_7x7_arrow_right.gif" server="www.sypdevelopment.com/dpm/" local="3322782828" remote="115087109876" /><file name="454545_7x7_arrow_up.gif" server="www.sypdevelopment.com/dpm/" local="3322782828" remote="102202207988" /><file name="888888_11x11_icon_arrows_leftright.gif" server="www.sypdevelopment.com/dpm/" local="3322782828" remote="166626717428" /><file name="888888_11x11_icon_arrows_updown.gif" server="www.sypdevelopment.com/dpm/" local="3322782828" remote="153741815540" /><file name="888888_11x11_icon_close.gif" server="www.sypdevelopment.com/dpm/" local="3322782828" remote="119382077172" /><file name="888888_11x11_icon_doc.gif" server="www.sypdevelopment.com/dpm/" local="3322782828" remote="110792142580" /><file name="888888_11x11_icon_folder_closed.gif" server="www.sypdevelopment.com/dpm/" local="3322782828" remote="153741815540" /><file name="888888_11x11_icon_folder_open.gif" server="www.sypdevelopment.com/dpm/" local="3322782828" remote="145151880948" /><file name="888888_11x11_icon_minus.gif" server="www.sypdevelopment.com/dpm/" local="3322782828" remote="119382077172" /><file name="888888_11x11_icon_plus.gif" server="www.sypdevelopment.com/dpm/" local="3322782828" remote="115087109876" /><file name="888888_7x7_arrow_down.gif" server="www.sypdevelopment.com/dpm/" local="3322782828" remote="110792142580" /><file name="888888_7x7_arrow_left.gif" server="www.sypdevelopment.com/dpm/" local="3322782828" remote="110792142580" /><file name="888888_7x7_arrow_right.gif" server="www.sypdevelopment.com/dpm/" local="3322782828" remote="115087109876" /><file name="888888_7x7_arrow_up.gif" server="www.sypdevelopment.com/dpm/" local="3322782828" remote="102202207988" /><file name="bg.gif" server="www.sypdevelopment.com/dpm/" local="3322782828" remote="29187763956" /><file name="custom_background.png" server="www.sypdevelopment.com/dpm/" local="3322782828" remote="93612273396" /><file name="custom_hex.png" server="www.sypdevelopment.com/dpm/" local="3322782828" remote="63547502324" /><file name="custom_hsb_b.png" server="www.sypdevelopment.com/dpm/" local="3322782828" remote="72137436916" /><file name="custom_hsb_h.png" server="www.sypdevelopment.com/dpm/" local="3322782828" remote="72137436916" /><file name="custom_hsb_s.png" server="www.sypdevelopment.com/dpm/" local="3322782828" remote="72137436916" /><file name="custom_indic.gif" server="www.sypdevelopment.com/dpm/" local="3322782828" remote="72137436916" /><file name="custom_rgb_b.png" server="www.sypdevelopment.com/dpm/" local="3322782828" remote="72137436916" /><file name="custom_rgb_g.png" server="www.sypdevelopment.com/dpm/" local="3322782828" remote="72137436916" /><file name="custom_rgb_r.png" server="www.sypdevelopment.com/dpm/" local="3322782828" remote="72137436916" /><file name="custom_submit.png" server="www.sypdevelopment.com/dpm/" local="3322782828" remote="76432404212" /><file name="dadada_40x100_textures_02_glass_75.png" server="www.sypdevelopment.com/dpm/" local="3322782828" remote="166626717428" /><file name="e6e6e6_40x100_textures_02_glass_75.png" server="www.sypdevelopment.com/dpm/" local="3322782828" remote="166626717428" /><file name="ffffff_40x100_textures_02_glass_65.png" server="www.sypdevelopment.com/dpm/" local="3322782828" remote="166626717428" /><file name="progress-bg.gif" server="www.sypdevelopment.com/dpm/" local="3322782828" remote="67842469620" /><file name="select.png" server="www.sypdevelopment.com/dpm/" local="3322782828" remote="46367633140" /><file name="select2.png" server="www.sypdevelopment.com/dpm/" local="3322782828" remote="50662600436" /><file name="spinner-bg.gif" server="www.sypdevelopment.com/dpm/" local="3322782828" remote="63547502324" /></dwsync>