<?xml version="1.0" encoding="utf-8" ?><dwsync><file name="block-editing-rtl.css" server="www.syptest.com/syptest.com/" local="3332909032" remote="93571367136" Dst="-1" /><file name="block-editing.css" server="www.syptest.com/syptest.com/" local="3340274486" remote="76391497952" Dst="-1" /><file name="blocks.css" server="www.syptest.com/syptest.com/" local="3340263939" remote="46326726880" Dst="-1" /><file name="comments.css" server="www.syptest.com/syptest.com/" local="3339953660" remote="54916661472" Dst="-1" /><file name="drupal6-reference.css" server="www.syptest.com/syptest.com/" local="3332895915" remote="93571367136" Dst="-1" /><file name="fields.css" server="www.syptest.com/syptest.com/" local="3332909032" remote="46326726880" Dst="-1" /><file name="forms-rtl.css" server="www.syptest.com/syptest.com/" local="3332911062" remote="59211628768" Dst="-1" /><file name="forms.css" server="www.syptest.com/syptest.com/" local="3332911062" remote="42031759584" Dst="-1" /><file name="html-reset-rtl.css" server="www.syptest.com/syptest.com/" local="3332944166" remote="80686465248" Dst="-1" /><file name="ie.css" server="www.syptest.com/syptest.com/" local="3346863112" remote="29146857696" Dst="-1" /><file name="ie6-rtl.css" server="www.syptest.com/syptest.com/" local="3332909032" remote="50621694176" Dst="-1" /><file name="ie6.css" server="www.syptest.com/syptest.com/" local="3340210610" remote="33441824992" Dst="-1" /><file name="layout-fixed-rtl.css" server="www.syptest.com/syptest.com/" local="3340210610" remote="89276399840" Dst="-1" /><file name="layout-fixed.css" server="www.syptest.com/syptest.com/" local="3340267793" remote="72096530656" Dst="-1" /><file name="layout-liquid-rtl.css" server="www.syptest.com/syptest.com/" local="3340210610" remote="93571367136" Dst="-1" /><file name="layout-liquid.css" server="www.syptest.com/syptest.com/" local="3340267793" remote="76391497952" Dst="-1" /><file name="messages-rtl.css" server="www.syptest.com/syptest.com/" local="3332911062" remote="72096530656" Dst="-1" /><file name="messages.css" server="www.syptest.com/syptest.com/" local="3332911062" remote="54916661472" Dst="-1" /><file name="navigation.css" server="www.syptest.com/syptest.com/" local="3340208561" remote="63506596064" Dst="-1" /><file name="nodes.css" server="www.syptest.com/syptest.com/" local="3340021049" remote="42031759584" Dst="-1" /><file name="page-backgrounds.css" server="www.syptest.com/syptest.com/" local="3340213069" remote="89276399840" Dst="-1" /><file name="pages-rtl.css" server="www.syptest.com/syptest.com/" local="3340264022" remote="59211628768" Dst="-1" /><file name="pages.css" server="www.syptest.com/syptest.com/" local="3360417538" remote="42031759584" Dst="-1" /><file name="panels-styles.css" server="www.syptest.com/syptest.com/" local="3343476714" remote="76391497952" Dst="-1" /><file name="print.css" server="www.syptest.com/syptest.com/" local="3360411364" remote="42031759584" Dst="-1" /><file name="README.txt" server="www.syptest.com/syptest.com/" local="3332904586" remote="46326726880" Dst="-1" /><file name="tabs-rtl.css" server="www.syptest.com/syptest.com/" local="3332909033" remote="54916661472" Dst="-1" /><file name="tabs.css" server="www.syptest.com/syptest.com/" local="3332909033" remote="37736792288" Dst="-1" /><file name="views-styles.css" server="www.syptest.com/syptest.com/" local="3332895915" remote="72096530656" Dst="-1" /><file name="wireframes.css" server="www.syptest.com/syptest.com/" local="3340213271" remote="63506596064" Dst="-1" /><file name="block-editing-rtl.css" server="www.sypdevelopment.com/dpm/" local="3378147273" remote="93572462556" Dst="-1" /><file name="block-editing.css" server="www.sypdevelopment.com/dpm/" local="3378147273" remote="76392593372" Dst="-1" /><file name="blocks.css" server="www.sypdevelopment.com/dpm/" local="3378147273" remote="46327822300" Dst="-1" /><file name="comments.css" server="www.sypdevelopment.com/dpm/" local="3378147273" remote="54917756892" Dst="-1" /><file name="drupal6-reference.css" server="www.sypdevelopment.com/dpm/" local="3378147273" remote="93572462556" Dst="-1" /><file name="fields.css" server="www.sypdevelopment.com/dpm/" local="3378147273" remote="46327822300" Dst="-1" /><file name="forms-rtl.css" server="www.sypdevelopment.com/dpm/" local="3378147273" remote="59212724188" Dst="-1" /><file name="forms.css" server="www.sypdevelopment.com/dpm/" local="3378147273" remote="42032855004" Dst="-1" /><file name="html-reset-rtl.css" server="www.sypdevelopment.com/dpm/" local="3378147273" remote="80687560668" Dst="-1" /><file name="ie.css" server="www.sypdevelopment.com/dpm/" local="3378147273" remote="29147953116" Dst="-1" /><file name="ie6-rtl.css" server="www.sypdevelopment.com/dpm/" local="3378147273" remote="50622789596" Dst="-1" /><file name="ie6.css" server="www.sypdevelopment.com/dpm/" local="3378147273" remote="33442920412" Dst="-1" /><file name="layout-fixed-rtl.css" server="www.sypdevelopment.com/dpm/" local="3378147273" remote="89277495260" Dst="-1" /><file name="layout-fixed.css" server="www.sypdevelopment.com/dpm/" local="3378996328" remote="2099393727199401532" Dst="-1" /><file name="layout-liquid-rtl.css" server="www.sypdevelopment.com/dpm/" local="3378147273" remote="93572462556" Dst="-1" /><file name="layout-liquid.css" server="www.sypdevelopment.com/dpm/" local="3378147273" remote="76392593372" Dst="-1" /><file name="messages-rtl.css" server="www.sypdevelopment.com/dpm/" local="3378147273" remote="72097626076" Dst="-1" /><file name="messages.css" server="www.sypdevelopment.com/dpm/" local="3378147273" remote="54917756892" Dst="-1" /><file name="navigation.css" server="www.sypdevelopment.com/dpm/" local="3378147273" remote="63507691484" Dst="-1" /><file name="nodes.css" server="www.sypdevelopment.com/dpm/" local="3378147273" remote="42032855004" Dst="-1" /><file name="page-backgrounds.css" server="www.sypdevelopment.com/dpm/" local="3378147273" remote="89277495260" Dst="-1" /><file name="pages-rtl.css" server="www.sypdevelopment.com/dpm/" local="3378147273" remote="59212724188" Dst="-1" /><file name="pages.css" server="www.sypdevelopment.com/dpm/" local="3378147273" remote="42032855004" Dst="-1" /><file name="panels-styles.css" server="www.sypdevelopment.com/dpm/" local="3378147273" remote="76392593372" Dst="-1" /><file name="print.css" server="www.sypdevelopment.com/dpm/" local="3378147273" remote="42032855004" Dst="-1" /><file name="README.txt" server="www.sypdevelopment.com/dpm/" local="3378147273" remote="46327822300" Dst="-1" /><file name="tabs-rtl.css" server="www.sypdevelopment.com/dpm/" local="3378147273" remote="54917756892" Dst="-1" /><file name="tabs.css" server="www.sypdevelopment.com/dpm/" local="3378147273" remote="37737887708" Dst="-1" /><file name="views-styles.css" server="www.sypdevelopment.com/dpm/" local="3378147273" remote="72097626076" Dst="-1" /><file name="wireframes.css" server="www.sypdevelopment.com/dpm/" local="3378999210" remote="2115647687333732732" Dst="-1" /><file name="mf-webfonts.css" server="50.22.70.60/dpm/" local="3390397662" remote="2643476748294247072" Dst="-1" /><file name="layout-fixed.css" server="50.22.70.60/dpm/" local="3390918210" remote="2427639678004707348" Dst="-1" /><file name="block-editing.css" server="50.22.70.60/dpm/" local="3390841646" remote="431103222558233860" Dst="-1" /><file name="html-reset.css" server="www.sypdevelopment.com/dpm/" local="3417788106" remote="426742370490859700" Dst="-1" /><file name="html-reset.css" server="50.22.115.91/httpdocs/" local="3447250449" remote="318763443840161352" Dst="-1" /><file name="layout-fixed.css" server="50.22.115.91/httpdocs/" local="3420472256" remote="3552309162645927348" Dst="-1" /><file name="html-reset.css" server="www.dpm-inc.com/httpdocs/" local="3474457630" remote="7769421316" Dst="-1" /></dwsync>